navvy/__init__.py
navvy/navvy.py
navvy-2.0.1.dist-info/LICENSE
navvy-2.0.1.dist-info/METADATA
navvy-2.0.1.dist-info/WHEEL
navvy-2.0.1.dist-info/top_level.txt
navvy-2.0.1.dist-info/RECORD
