Metadata-Version: 2.2
Name: navvy
Version: 2.0.1
Summary: Automation tool for managing Git repositories with LLMs.
Author-email: Rofly António <mitangerofly@gmail.com>
License: MIT License
Project-URL: Homepage, https://github.com/itsrofly/navvy-package
Keywords: automation,ai,openai,git,code
Classifier: License :: OSI Approved :: MIT License
Classifier: Programming Language :: Python
Classifier: Programming Language :: Python :: 3
Requires-Python: >=3.8
License-File: LICENSE
Requires-Dist: annotated-types==0.7.0
Requires-Dist: anyio==4.6.2.post1
Requires-Dist: certifi==2024.8.30
Requires-Dist: distro==1.9.0
Requires-Dist: gitdb==4.0.11
Requires-Dist: GitPython==3.1.43
Requires-Dist: h11==0.14.0
Requires-Dist: httpcore==1.0.7
Requires-Dist: httpx==0.27.2
Requires-Dist: idna==3.10
Requires-Dist: jiter==0.7.1
Requires-Dist: openai==1.63.2
Requires-Dist: pydantic==2.10.6
Requires-Dist: pydantic-core==2.27.2
Requires-Dist: smmap==5.0.1
Requires-Dist: sniffio==1.3.1
Requires-Dist: tqdm==4.67.0
Requires-Dist: typing_extensions==4.12.2
Requires-Dist: pydantic-ai==0.0.24
